JapaneseForMatplotlib/__init__.py
JapaneseForMatplotlib/font_manager.py
JapaneseMatplotlib/__init__.py
JapaneseMatplotlib/font_manager.py
JapaneseMatplotlib/fonts/ipaexg.ttf
JapaneseMatplotlib-1.0.5.dist-info/METADATA
JapaneseMatplotlib-1.0.5.dist-info/WHEEL
JapaneseMatplotlib-1.0.5.dist-info/top_level.txt
JapaneseMatplotlib-1.0.5.dist-info/RECORD
