Metadata-Version: 2.1
Name: JapaneseMatplotlib
Version: 1.0.5
Summary: A package to support Japanese fonts for Matplotlib
Author: kiendt
Author-email: kiendt226@gmail.com
License: MIT License
Requires-Dist: matplotlib
